by_config/__init__.py
by_config/config.py
by_config/loader.py
by_config/py.typed
by_config/typed.py
by_tech_config-0.1.5.dist-info/METADATA
by_tech_config-0.1.5.dist-info/WHEEL
by_tech_config-0.1.5.dist-info/top_level.txt
by_tech_config-0.1.5.dist-info/RECORD
