Metadata-Version: 2.4
Name: by_tech_config
Version: 0.1.5
Summary: YAML/JSON配置加载器
Author-email: Evanston <kaluoshilong@qq.com>
License: MIT
Project-URL: Homepage, https://github.com/Evan-acg/beny-py-config
Requires-Python: >=3.11
Requires-Dist: pyyaml>=6.0.2
Requires-Dist: watchdog>=6.0.0
